<?xml version="1.0" encoding="UTF-8"?>
<!DOCTYPE hibernate-mapping PUBLIC "-//Hibernate/Hibernate Mapping DTD 3.0//EN"
	"http://hibernate.sourceforge.net/hibernate-mapping-3.0.dtd">

<!-- This file generated by Sakai App Builder -AZ -->
<hibernate-mapping>

   <!-- put your value object in the class name, 
      the table name is optional but you should specify it to avoid collisions -->
      
   <class name="co.edu.javeriana.ASHYI.hbm.GrafoRelacionesImpl" table="Grafo_Relaciones">
       <composite-id>
			<key-many-to-one name="idGrafo" class="co.edu.javeriana.ASHYI.hbm.GrafoImpl">
				<column name="IDGRAFO" />
			</key-many-to-one>
			<key-property name="idRelacionGrafo" type="int">
				<column name="IDRELACIONGRAFO" />
			</key-property>
		</composite-id>
        <property name="idItemPlan_Destino" type="int">
            <column name="idItemPlan_Destino" />
        </property>        
        <property name="idItemPlan_Origen" type="int">
            <column name="idItemPlan_Origen" />
        </property>
        <property name="orden" type="int">
            <column name="orden" />
        </property>
   </class>
</hibernate-mapping>